optima35/__init__.py
optima35/__main__.py
optima35/core.py
optima35/image_handler.py
optima35-1.1.4.dist-info/METADATA
optima35-1.1.4.dist-info/WHEEL
optima35-1.1.4.dist-info/entry_points.txt
optima35-1.1.4.dist-info/licenses/LICENSE.md
optima35-1.1.4.dist-info/RECORD
